slprint/__init__.py
slprint/slowprint.py
slprint_pkg-1.0.dist-info/LICENSE
slprint_pkg-1.0.dist-info/METADATA
slprint_pkg-1.0.dist-info/WHEEL
slprint_pkg-1.0.dist-info/top_level.txt
slprint_pkg-1.0.dist-info/RECORD
