Metadata-Version: 2.1
Name: slprint-pkg
Version: 1.0
Summary: Simple module to display a text with a time interval between each characters.
Home-page: https://github.com/RonaldoVasques/slowprint
Author: Ronaldo Augusto Vasques de Souza
Author-email: vasquessouza.75@gmail.com
License: MIT License
